[
    {
        "Title": "Account & Finance",
        "Id" : 1,
        "JobsPresent": 1500,
        "image": "https://images.unsplash.com/photo-1597636509409-52abe462d08c?ixlib=rb-4.0.3&ixid=M3wxMjA3fDB8MHxwaG90by1wYWdlfHx8fGVufDB8fHx8fA%3D%3D&auto=format&fit=crop&w=2070&q=80"
    },
    {
        "Title": "Creative Design",
        "Id" : 2,
        "JobsPresent": 100,
        "image": "https://images.unsplash.com/photo-1499951360447-b19be8fe80f5?ixlib=rb-4.0.3&ixid=M3wxMjA3fDB8MHxwaG90by1wYWdlfHx8fGVufDB8fHx8fA%3D%3D&auto=format&fit=crop&w=1170&q=80"
    },
    {
        "Title": "Marketing & Sales",
        "Id" : 3,
        "JobsPresent": 224,
        "image": "https://images.unsplash.com/photo-1580828343064-fde4fc206bc6?ixlib=rb-4.0.3&ixid=M3wxMjA3fDB8MHxwaG90by1wYWdlfHx8fGVufDB8fHx8fA%3D%3D&auto=format&fit=crop&w=1171&q=80"
    },
    {
        "Title": "Engneering Jobs",
        "Id" : 4,
        "JobsPresent": 15000,
        "image": "https://images.unsplash.com/photo-1455165814004-1126a7199f9b?ixlib=rb-4.0.3&ixid=M3wxMjA3fDB8MHxwaG90by1wYWdlfHx8fGVufDB8fHx8fA%3D%3D&auto=format&fit=crop&w=1170&q=80"
    }
]